snapfront_coherence/__init__.py
snapfront_coherence/client.py
snapfront_coherence/errors.py
snapfront_coherence-0.2.7.dist-info/licenses/LICENSE
snapfront_coherence-0.2.7.dist-info/METADATA
snapfront_coherence-0.2.7.dist-info/WHEEL
snapfront_coherence-0.2.7.dist-info/top_level.txt
snapfront_coherence-0.2.7.dist-info/RECORD
